zeekpkg/__init__.py
zeekpkg/_util.py
zeekpkg/manager.py
zeekpkg/package.py
zeekpkg/source.py
zeekpkg/template.py
zeekpkg/uservar.py
zkg-3.1.0.data/data/output_dir/VERSION
zkg-3.1.0.data/scripts/zkg
zkg-3.1.0.dist-info/COPYING
zkg-3.1.0.dist-info/METADATA
zkg-3.1.0.dist-info/WHEEL
zkg-3.1.0.dist-info/top_level.txt
zkg-3.1.0.dist-info/RECORD
