Metadata-Version: 2.1
Name: zkg
Version: 3.1.0
Summary: The Zeek Package Manager
Maintainer-email: The Zeek Project <info@zeek.org>
License: Copyright (c) 2016 The Board of Trustees of the University of Illinois.
Project-URL: Homepage, https://docs.zeek.org/projects/package-manager
Project-URL: Repository, https://github.com/zeek/package-manager
Keywords: zeek,zeekctl,zeekcontrol,package,manager,scripts,plugins,security
Classifier: Development Status :: 5 - Production/Stable
Classifier: Environment :: Console
Classifier: License :: OSI Approved :: University of Illinois/NCSA Open Source License
Classifier: Operating System :: POSIX :: Linux
Classifier: Operating System :: MacOS :: MacOS X
Classifier: Programming Language :: Python :: 3
Classifier: Topic :: System :: Networking :: Monitoring
Classifier: Topic :: Utilities
Requires-Python: >=3.9
License-File: COPYING
Requires-Dist: GitPython >=3.1.43
Requires-Dist: btest >=1.1
Requires-Dist: semantic-version >=2.10.0
Provides-Extra: dev
Requires-Dist: Sphinx >=7.2.6 ; extra == 'dev'
Requires-Dist: sphinx-rtd-theme >=2.0.0 ; extra == 'dev'
